WhPy/__init__.py
WhPy/discord.py
WhPy/slack.py
WhPy-0.1.6.dist-info/LICENSE
WhPy-0.1.6.dist-info/METADATA
WhPy-0.1.6.dist-info/WHEEL
WhPy-0.1.6.dist-info/top_level.txt
WhPy-0.1.6.dist-info/RECORD
