Metadata-Version: 2.1
Name: WhPy
Version: 0.1.6
Summary: A Python 3 webhook module.
Home-page: https://github.com/MichaelCduBois/WhPy
Author: Michael duBois
Author-email: mdubois@mcduboiswebservices.com
License: UNKNOWN
Platform: UNKNOWN
Classifier: Development Status :: 3 - Alpha
Classifier: Intended Audience :: Developers
Classifier: Natural Language :: English
Classifier: License :: OSI Approved :: MIT License
Classifier: Programming Language :: Python :: 3.7
Classifier: Operating System :: OS Independent
Requires-Dist: requests (==2.22.0)
